hardware/adder_doble/hdl/adder.sv
`timescale 1ns/1ps

module adder #(
    parameter integer DATA_W = 4
)(
    input logic unsigned[DATA_W -1 :0] A,
    input logic unsigned[DATA_W -1 :0] B,
    input logic Carry,
    output logic unsigned[DATA_W  :0] X
);
    assign X = A + B + {3'b0,Carry};
endmodule

hardware/adder_doble/hdl/adder_doble.sv
`timescale 1ns/1ps

module adder_doble (
    input logic unsigned[7 :0] A,
    input logic unsigned[7: 0] B, 
    output logic unsigned[8: 0] X
);
    wire [4 :0] X1_o;
    wire [4 :0] X2_o;

    adder #(.DATA_W(4)) adder_1 (
        .A(A[3:0]),
        .B(B[3:0]),
        .Carry(1'b0),
        .X(X1_o)
    );
    adder #(.DATA_W(4)) adder_2 (
        .A(A[7:4]),
        .B(B[7:4]),
        .Carry(X1_o[4]),
        .X(X2_o)
    );

    assign X = {X2_o, X1_o[3:0]};
endmodule

examples/adder_doble/tests/dump.vcd
$version Generated by VerilatedVcd $end
$timescale 1ps $end
 $scope module  $end
  $var wire 8 # A [7:0] $end
  $var wire 8 $ B [7:0] $end
  $var wire 9 % X [8:0] $end
  $scope module adder_doble $end
   $var wire 8 & A [7:0] $end
   $var wire 8 ' B [7:0] $end
   $var wire 9 ( X [8:0] $end
   $var wire 5 ) X1_o [4:0] $end
   $var wire 5 * X2_o [4:0] $end
   $scope module adder_1 $end
    $var wire 32 3 DATA_W [31:0] $end
    $var wire 4 + A [3:0] $end
    $var wire 4 , B [3:0] $end
    $var wire 1 - Carry $end
    $var wire 5 . X [4:0] $end
   $upscope $end
   $scope module adder_2 $end
    $var wire 32 3 DATA_W [31:0] $end
    $var wire 4 / A [3:0] $end
    $var wire 4 0 B [3:0] $end
    $var wire 1 1 Carry $end
    $var wire 5 2 X [4:0] $end
   $upscope $end
  $upscope $end
 $upscope $end
$enddefinitions $end


#0
b00000101 #
b00001010 $
b000001111 %
b00000101 &
b00001010 '
b000001111 (
b01111 )
b00000 *
b0101 +
b1010 ,
0-
b01111 .
b0000 /
b0000 0
01
b00000 2
b00000000000000000000000000000100 3
#2000
#2001
b10010110 #
b11110100 $
b110001010 %
b10010110 &
b11110100 '
b110001010 (
b01010 )
b11000 *
b0110 +
b0100 ,
b01010 .
b1001 /
b1111 0
b11000 2
#4001
b11001010 #
b11100001 $
b110101011 %
b11001010 &
b11100001 '
b110101011 (
b01011 )
b11010 *
b1010 +
b0001 ,
b01011 .
b1100 /
b1110 0
b11010 2
#6001
b01000101 #
b10001101 $
b011010010 %
b01000101 &
b10001101 '
b011010010 (
b10010 )
b01101 *
b0101 +
b1101 ,
b10010 .
b0100 /
b1000 0
11
b01101 2
#8001
b11011111 #
b00011111 $
b011111110 %
b11011111 &
b00011111 '
b011111110 (
b11110 )
b01111 *
b1111 +
b1111 ,
b11110 .
b1101 /
b0001 0
b01111 2
#10001
b11101100 #
b11010000 $
b110111100 %
b11101100 &
b11010000 '
b110111100 (
b01100 )
b11011 *
b1100 +
b0000 ,
b01100 .
b1110 /
b1101 0
01
b11011 2
#12001
b00000110 #
b00111100 $
b001000010 %
b00000110 &
b00111100 '
b001000010 (
b10010 )
b00100 *
b0110 +
b1100 ,
b10010 .
b0000 /
b0011 0
11
b00100 2
#14001
b10110000 #
b11011001 $
b110001001 %
b10110000 &
b11011001 '
b110001001 (
b01001 )
b11000 *
b0000 +
b1001 ,
b01001 .
b1011 /
b1101 0
01
b11000 2
#16001
b01100111 #
b01110111 $
b011011110 %
b01100111 &
b01110111 '
b011011110 (
b01110 )
b01101 *
b0111 +
b0111 ,
b01110 .
b0110 /
b0111 0
b01101 2
#18001
b10010110 #
b00101101 $
b011000011 %
b10010110 &
b00101101 '
b011000011 (
b10011 )
b01100 *
b0110 +
b1101 ,
b10011 .
b1001 /
b0010 0
11
b01100 2
#20001
b11010110 #
b11010100 $
b110101010 %
b11010110 &
b11010100 '
b110101010 (
b01010 )
b11010 *
b0100 ,
b01010 .
b1101 /
b1101 0
01
b11010 2
